{
  "symbol": "ABLBL.NS",
  "period": "quarterly",
  "data": [
    {
      "ticker": "ABLBL.NS",
      "date": "2024-06-30",
      "quarter": "Q2 2024",
      "fiscal_year": 2024,
      "revenue": 17844700000.0,
      "gross_profit": 10503100000.0,
      "operating_income": 4959500000.0,
      "ebitda": 2829100000.0,
      "net_income": 229300000.0,
      "diluted_eps": null,
      "total_assets": null,
      "total_liabilities": null,
      "total_equity": null,
      "total_debt": null,
      "cash_and_equivalents": null,
      "current_assets": null,
      "current_liabilities": null,
      "operating_cash_flow": null,
      "investing_cash_flow": null,
      "financing_cash_flow": null,
      "free_cash_flow": null,
      "capex": null,
      "pe_ratio": 44.278572,
      "peg_ratio": null,
      "pb_ratio": 11.6731,
      "ps_ratio": 1.8944951,
      "price_target_high": 175.0,
      "price_target_low": 142.0,
      "price_target_avg": 160.11111,
      "promoter_holding": 0.56513,
      "institutional_holding": 0,
      "eps_estimate": null,
      "next_earnings_date": null,
      "last_buyback_date": null,
      "dividends": null,
      "splits": null,
      "buybacks": null,
      "debt_to_equity": null,
      "current_ratio": null,
      "operating_margin": 27.792565859891173,
      "net_profit_margin": 1.2849753708384002,
      "roe": null,
      "roa": null,
      "debt_to_fcf_ratio": null,
      "ebitda_margin": 15.85400707212786,
      "revenue_growth_yoy": null,
      "ebitda_growth_yoy": null
    },
    {
      "ticker": "ABLBL.NS",
      "date": "2025-06-30",
      "quarter": "Q2 2025",
      "fiscal_year": 2025,
      "revenue": 18405800000.0,
      "gross_profit": 11522600000.0,
      "operating_income": 5547500000.0,
      "ebitda": 2856500000.0,
      "net_income": 240600000.0,
      "diluted_eps": null,
      "total_assets": null,
      "total_liabilities": null,
      "total_equity": null,
      "total_debt": null,
      "cash_and_equivalents": null,
      "current_assets": null,
      "current_liabilities": null,
      "operating_cash_flow": null,
      "investing_cash_flow": null,
      "financing_cash_flow": null,
      "free_cash_flow": null,
      "capex": null,
      "pe_ratio": 44.278572,
      "peg_ratio": null,
      "pb_ratio": 11.6731,
      "ps_ratio": 1.8944951,
      "price_target_high": 175.0,
      "price_target_low": 142.0,
      "price_target_avg": 160.11111,
      "promoter_holding": 0.56513,
      "institutional_holding": 0,
      "eps_estimate": null,
      "next_earnings_date": null,
      "last_buyback_date": null,
      "dividends": null,
      "splits": null,
      "buybacks": null,
      "debt_to_equity": null,
      "current_ratio": null,
      "operating_margin": 30.139955883471515,
      "net_profit_margin": 1.3071966445359615,
      "roe": null,
      "roa": null,
      "debt_to_fcf_ratio": null,
      "ebitda_margin": 15.519564485107956,
      "revenue_growth_yoy": null,
      "ebitda_growth_yoy": null
    }
  ]
}